ufiles/__init__.py
ufiles/async_ufiles.py
ufiles/schemas.py
ufiles/services.py
ufiles/ufiles.py
ufiles-0.2.13.dist-info/LICENSE.txt
ufiles-0.2.13.dist-info/METADATA
ufiles-0.2.13.dist-info/WHEEL
ufiles-0.2.13.dist-info/top_level.txt
ufiles-0.2.13.dist-info/RECORD
