Metadata-Version: 2.1
Name: ufiles
Version: 0.2.13
Summary: A client for Ufiles.
Author-email: Mahdi Kiani <mahdikiany@gmail.com>
Maintainer-email: Mahdi Kiani <mahdikiany@gmail.com>
License: Copyright (c) 2016 The Python Packaging Authority (PyPA)
Project-URL: Homepage, https://github.com/ufilesorg/ufiles-python
Project-URL: Bug Reports, https://github.com/ufilesorg/ufiles-python/issues
Project-URL: Funding, https://github.com/ufilesorg/ufiles-python
Project-URL: Say Thanks!, https://saythanks.io/to/mahdikiani
Project-URL: Source, https://github.com/ufilesorg/ufiles-python
Keywords: ufiles,usso,object storage,upload,media
Classifier: Development Status :: 3 - Alpha
Classifier: Intended Audience :: Developers
Classifier: Topic :: Software Development :: Build Tools
Classifier: License :: OSI Approved :: MIT License
Classifier: Programming Language :: Python :: 3
Classifier: Programming Language :: Python :: 3.10
Classifier: Programming Language :: Python :: 3.11
Classifier: Programming Language :: Python :: 3.12
Classifier: Programming Language :: Python :: 3 :: Only
Requires-Python: >=3.9
License-File: LICENSE.txt
Requires-Dist: pydantic>=2
Requires-Dist: requests>=2.26.0
Requires-Dist: pyjwt[crypto]
Requires-Dist: usso>=0.27.2
Requires-Dist: singleton_package
Requires-Dist: json-advanced
Requires-Dist: cachetools
